jotion/__init__.py
jotion-0.0.0.dist-info/LICENSE
jotion-0.0.0.dist-info/WHEEL
jotion-0.0.0.dist-info/METADATA
jotion-0.0.0.dist-info/RECORD
